{"version":1,"resource":"file:///home/m4cren/webDev/ReactCourse/client/src/components/expenseTracker/Main.tsx","entries":[{"id":"oL18.tsx","timestamp":1747543421556},{"id":"e5KN.tsx","timestamp":1747545005235},{"id":"DRio.tsx","timestamp":1747545587478},{"id":"PNPo.tsx","timestamp":1747547479900},{"id":"C51C.tsx","timestamp":1747547937271},{"id":"lxLF.tsx","timestamp":1747547958533},{"id":"SKlA.tsx","timestamp":1747548423614},{"id":"FNlk.tsx","timestamp":1747548682741},{"id":"Bxbs.tsx","timestamp":1747548733059},{"id":"82ow.tsx","source":"undoRedo.source","timestamp":1747548754226},{"id":"PR9V.tsx","timestamp":1747548800935},{"id":"ToOX.tsx","timestamp":1747548843016},{"id":"bOVA.tsx","timestamp":1747548901042},{"id":"3dNi.tsx","timestamp":1747549054306},{"id":"glxh.tsx","timestamp":1747549073386},{"id":"qhqk.tsx","timestamp":1747549106231},{"id":"Kodz.tsx","timestamp":1747549942018},{"id":"vana.tsx","timestamp":1747550076483},{"id":"AkYH.tsx","timestamp":1747550638982},{"id":"psSV.tsx","timestamp":1747551296279},{"id":"5k51.tsx","timestamp":1747551588505},{"id":"8gvQ.tsx","timestamp":1747552063026},{"id":"gL4Z.tsx","timestamp":1747552277736},{"id":"QI3c.tsx","timestamp":1747552325089},{"id":"RvvD.tsx","timestamp":1747552342913},{"id":"w7WL.tsx","timestamp":1747552378789}]}